UOpenCV/UOpenCV.py
UOpenCV/UOpenCVUtil.py
UOpenCV/__init__.py
UOpenCV/test.py
UOpenCV-1.0.0.dist-info/METADATA
UOpenCV-1.0.0.dist-info/WHEEL
UOpenCV-1.0.0.dist-info/top_level.txt
UOpenCV-1.0.0.dist-info/RECORD
